django_excel_to_model/__init__.py
django_excel_to_model/admin.py
django_excel_to_model/default_settings.py
django_excel_to_model/django_app_generator.py
django_excel_to_model/field_tools.py
django_excel_to_model/forms.py
django_excel_to_model/models.py
django_excel_to_model/openpyxl_reader.py
django_excel_to_model/reader.py
django_excel_to_model/tasks.py
django_excel_to_model/urls.py
django_excel_to_model/views.py
django_excel_to_model/views_import.py
django_excel_to_model/xlsb_reader.py
django_excel_to_model/file_readers/__init__.py
django_excel_to_model/file_readers/csv_reader.py
django_excel_to_model/file_readers/data_file_base.py
django_excel_to_model/file_readers/data_source_base.py
django_excel_to_model/file_readers/data_source_factory.py
django_excel_to_model/file_readers/file_reader_exceptions.py
django_excel_to_model/management/__init__.py
django_excel_to_model/management/commands/__init__.py
django_excel_to_model/management/commands/dump_excel_to_mapping.py
django_excel_to_model/management/commands/import_excel_according_to_model.py
django_excel_to_model/management/commands/model_create_utils/__init__.py
django_excel_to_model/management/commands/model_create_utils/attribute_generator.py
django_excel_to_model/management/commands/model_create_utils/django_tables2_utils.py
django_excel_to_model/management/commands/utils/__init__.py
django_excel_to_model/management/commands/utils/bulk_inserter.py
django_excel_to_model/management/commands/utils/counter.py
django_excel_to_model/management/commands/utils/single_inserter.py
django_excel_to_model/migrations/0001_initial.py
django_excel_to_model/migrations/__init__.py
django_excel_to_model/south_migrations/__init__.py
django_excel_to_model/static/css/django_excel_to_model.css
django_excel_to_model/static/js/django_excel_to_model.js
django_excel_to_model/templates/django_excel_to_model/base.html
django_excel_to_model/templates/django_excel_to_model/upload.html
django_excel_to_model-0.1.12.dist-info/AUTHORS.rst
django_excel_to_model-0.1.12.dist-info/LICENSE
django_excel_to_model-0.1.12.dist-info/METADATA
django_excel_to_model-0.1.12.dist-info/WHEEL
django_excel_to_model-0.1.12.dist-info/top_level.txt
django_excel_to_model-0.1.12.dist-info/RECORD
