Metadata-Version: 2.1
Name: django-excel-to-model
Version: 0.1.12
Summary: Create model file from excel
Home-page: https://github.com/weijia/django-excel-to-model
Author: Wang Weijia
Author-email: richardwangwang@gmail.com
License: BSD
Keywords: django-excel-to-model
Platform: UNKNOWN
Classifier: Development Status :: 3 - Alpha
Classifier: Framework :: Django
Classifier: Framework :: Django :: 1.7
Classifier: Framework :: Django :: 1.8
Classifier: Intended Audience :: Developers
Classifier: License :: OSI Approved :: BSD License
Classifier: Natural Language :: English
Classifier: Programming Language :: Python :: 2
Classifier: Programming Language :: Python :: 2.7
Classifier: Programming Language :: Python :: 3
Classifier: Programming Language :: Python :: 3.3
Classifier: Programming Language :: Python :: 3.4
Classifier: Programming Language :: Python :: 3.5
Requires-Dist: django-background-tasks
Requires-Dist: pyxlsb
Requires-Dist: pinyin
